cedarkit/maps/__init__.py
cedarkit/maps/_version.py
cedarkit/maps/colormap.py
cedarkit/maps/graph.py
cedarkit/maps/util.py
cedarkit/maps/chart/__init__.py
cedarkit/maps/chart/chart.py
cedarkit/maps/chart/layer.py
cedarkit/maps/chart/panel.py
cedarkit/maps/domains/__init__.py
cedarkit/maps/domains/east_asia.py
cedarkit/maps/domains/ens_cn.py
cedarkit/maps/domains/europe_asia.py
cedarkit/maps/domains/global_domain.py
cedarkit/maps/domains/map_domain.py
cedarkit/maps/domains/north_polar.py
cedarkit/maps/domains/xy_domin.py
cedarkit/maps/map/__init__.py
cedarkit/maps/map/cemc.py
cedarkit/maps/map/default.py
cedarkit/maps/product/__init__.py
cedarkit/maps/product/east_asia.py
cedarkit/maps/product/europe_asia.py
cedarkit/maps/product/north_polar.py
cedarkit/maps/resources/colormap/ncl/BlAqGrYeOrReVi200.rgb
cedarkit/maps/resources/colormap/ncl/BlGrYeOrReVi200.rgb
cedarkit/maps/resources/colormap/ncl/WhBlGrYeRe.rgb
cedarkit/maps/resources/colormap/ncl/WhViBlGrYeOrRe.rgb
cedarkit/maps/resources/colormap/ncl/mch_default.rgb
cedarkit/maps/resources/colormap/ncl/ncl_colors.csv
cedarkit/maps/resources/colormap/ncl/prcp_3.rgb
cedarkit/maps/resources/colormap/ncl/precip_diff_12lev.rgb
cedarkit/maps/resources/colormap/ncl/rainbow+white+gray.gp
cedarkit/maps/resources/colormap/ncl/temp_19lev.rgb
cedarkit/maps/resources/colormap/ncl/wh-bl-gr-ye-re.rgb
cedarkit/maps/resources/map/china-shapefiles/README.md
cedarkit/maps/resources/map/china-shapefiles/shapefiles/china.dbf
cedarkit/maps/resources/map/china-shapefiles/shapefiles/china.prj
cedarkit/maps/resources/map/china-shapefiles/shapefiles/china.shp
cedarkit/maps/resources/map/china-shapefiles/shapefiles/china.shx
cedarkit/maps/resources/map/china-shapefiles/shapefiles/china_country.dbf
cedarkit/maps/resources/map/china-shapefiles/shapefiles/china_country.prj
cedarkit/maps/resources/map/china-shapefiles/shapefiles/china_country.shp
cedarkit/maps/resources/map/china-shapefiles/shapefiles/china_country.shx
cedarkit_maps-2024.4.0.dist-info/LICENSE
cedarkit_maps-2024.4.0.dist-info/METADATA
cedarkit_maps-2024.4.0.dist-info/WHEEL
cedarkit_maps-2024.4.0.dist-info/top_level.txt
cedarkit_maps-2024.4.0.dist-info/RECORD
